[{"id":360630,"name":"Cairo","nameKo":"카이로","ascii":"Cairo","lat":30.06263,"lon":31.24967,"population":9606916},{"id":361058,"name":"Alexandria","nameKo":"알렉산드리아","ascii":"Alexandria","lat":31.20176,"lon":29.91582,"population":5263542},{"id":360995,"name":"Giza","ascii":"Giza","lat":30.00944,"lon":31.20861,"population":4367343},{"id":349076,"name":"Shubrā al Khaymah","ascii":"Shubra al Khaymah","lat":30.12511,"lon":31.25053,"population":1240289},{"id":358619,"name":"Port Said","ascii":"Port Said","lat":31.26531,"lon":32.3019,"population":780515},{"id":359796,"name":"Suez","nameKo":"수에즈","ascii":"Suez","lat":29.97371,"lon":32.52627,"population":699541},{"id":353225,"name":"Madīnat an Naşr","ascii":"Madinat an Nasr","lat":30.06667,"lon":31.3,"population":668413},{"id":360761,"name":"Al Mansurah","ascii":"Al Mansurah","lat":31.03637,"lon":31.38069,"population":621953},{"id":360829,"name":"Al Maḩallah al Kubrá","ascii":"Al Mahallah al Kubra","lat":30.97063,"lon":31.1669,"population":592573},{"id":347497,"name":"Tanta","ascii":"Tanta","lat":30.78847,"lon":31.00192,"population":576648},{"id":359783,"name":"Assiut","ascii":"Assiut","lat":27.18096,"lon":31.18368,"population":528669},{"id":361320,"name":"Al Fayyum","ascii":"Al Fayyum","lat":29.30995,"lon":30.8418,"population":519047},{"id":360890,"name":"Al Khuşūş","ascii":"Al Khusus","lat":30.15293,"lon":31.31501,"population":488904},{"id":355449,"name":"Esna","ascii":"Esna","lat":25.29336,"lon":32.55402,"population":462787},{"id":359493,"name":"Zagazig","nameKo":"자가지그","ascii":"Zagazig","lat":30.58768,"lon":31.502,"population":430445},{"id":361055,"name":"Ismailia","nameKo":"이스마일리아","ascii":"Ismailia","lat":30.60427,"lon":32.27225,"population":429465},{"id":360502,"name":"Luxor","nameKo":"룩소르","ascii":"Luxor","lat":25.69893,"lon":32.6421,"population":422407},{"id":353802,"name":"Kom Ombo","ascii":"Kom Ombo","lat":24.47669,"lon":32.94626,"population":409311},{"id":359792,"name":"Aswān","nameKo":"아스완","ascii":"Aswan","lat":24.09082,"lon":32.89942,"population":379774},{"id":353219,"name":"6th of October City","ascii":"6th of October City","lat":29.81667,"lon":31.05,"population":368650},{"id":356436,"name":"Ḩadā’iq al Qubbah","ascii":"Hada'iq al Qubbah","lat":30.08843,"lon":31.28351,"population":339612},{"id":358448,"name":"Damanhur","ascii":"Damanhur","lat":31.03408,"lon":30.46823,"population":318207},{"id":8134081,"name":"Al Qāhirah al Jadīdah","ascii":"Al Qahirah al Jadidah","lat":30.04214,"lon":31.44446,"population":313139},{"id":7799991,"name":"New Cairo","ascii":"New Cairo","lat":30.03,"lon":31.47,"population":313139},{"id":358048,"name":"Damietta","nameKo":"다미에타","ascii":"Damietta","lat":31.41648,"lon":31.81332,"population":305920},{"id":350203,"name":"Rosetta","nameKo":"로제타","ascii":"Rosetta","lat":31.39951,"lon":30.41718,"population":301795},{"id":360686,"name":"Minya","ascii":"Minya","lat":28.09193,"lon":30.75813,"population":283605},{"id":359173,"name":"Banī Suwayf","ascii":"Bani Suwayf","lat":29.07441,"lon":31.09785,"population":273151},{"id":349158,"name":"Shibīn al Kawm","ascii":"Shibin al Kawm","lat":30.55258,"lon":31.00904,"population":267945},{"id":347796,"name":"Sohag","nameKo":"소하그","ascii":"Sohag","lat":26.55695,"lon":31.69478,"population":266944},{"id":350550,"name":"Qina","ascii":"Qina","lat":26.16418,"lon":32.72671,"population":252883},{"id":353229,"name":"Al ‘Āshir min Ramaḑān","nameKo":"라마단 10일시","ascii":"Al 'Ashir min Ramadan","lat":30.29636,"lon":31.74633,"population":246148},{"id":355795,"name":"Ḩalwān","ascii":"Halwan","lat":29.84144,"lon":31.30084,"population":230000},{"id":352951,"name":"Mallawī","ascii":"Mallawi","lat":27.73264,"lon":30.84129,"population":212628},{"id":361291,"name":"Hurghada","nameKo":"후르가다","ascii":"Hurghada","lat":27.25738,"lon":33.81291,"population":207132},{"id":361546,"name":"Arīsh","nameKo":"아리시","ascii":"Arish","lat":31.13159,"lon":33.79844,"population":199243},{"id":354502,"name":"Kafr ash Shaykh","ascii":"Kafr ash Shaykh","lat":31.11174,"lon":30.93991,"population":194569},{"id":358840,"name":"Bilbeis","nameKo":"빌베이스","ascii":"Bilbeis","lat":30.42039,"lon":31.56223,"population":185237},{"id":359280,"name":"Banhā","ascii":"Banha","lat":30.45977,"lon":31.1842,"population":182254},{"id":355628,"name":"Idkū","ascii":"Idku","lat":31.3073,"lon":30.2981,"population":177152},{"id":352733,"name":"Marsá Maţrūḩ","ascii":"Marsa Matruh","lat":31.3529,"lon":27.23725,"population":176498},{"id":360716,"name":"Al Maţarīyah","ascii":"Al Matariyah","lat":31.18287,"lon":32.03108,"population":162045},{"id":350789,"name":"Qalyub","ascii":"Qalyub","lat":30.17922,"lon":31.2056,"population":156363},{"id":361179,"name":"Al Ḩawāmidīyah","ascii":"Al Hawamidiyah","lat":29.9,"lon":31.25,"population":155055},{"id":362485,"name":"Abū Kabīr","ascii":"Abu Kabir","lat":30.72508,"lon":31.67148,"population":154466},{"id":352181,"name":"Mīt Ghamr","ascii":"Mit Ghamr","lat":30.71524,"lon":31.2592,"population":153754},{"id":361661,"name":"Akhmīm","ascii":"Akhmim","lat":26.5622,"lon":31.74566,"population":151430},{"id":355026,"name":"Girga","ascii":"Girga","lat":26.33721,"lon":31.89295,"population":151256},{"id":358108,"name":"Disūq","ascii":"Disuq","lat":31.13259,"lon":30.64784,"population":149291},{"id":349717,"name":"Samālūţ","ascii":"Samalut","lat":28.31214,"lon":30.71007,"population":142009},{"id":12451089,"name":"Al-'Ubūr","ascii":"Al-'Ubur","lat":30.22886,"lon":31.48149,"population":138987},{"id":353492,"name":"Kirdāsah","ascii":"Kirdasah","lat":30.03103,"lon":31.11109,"population":137588},{"id":358821,"name":"Bilqās","ascii":"Bilqas","lat":31.21452,"lon":31.35798,"population":137080},{"id":358600,"name":"Būsh","ascii":"Bush","lat":29.14816,"lon":31.12733,"population":136441},{"id":347634,"name":"Ţahţā","ascii":"Tahta","lat":26.76866,"lon":31.50198,"population":134314},{"id":347907,"name":"Sinnūris","ascii":"Sinnuris","lat":29.41345,"lon":30.86579,"population":133532},{"id":354775,"name":"Kafr ad Dawwār","ascii":"Kafr ad Dawwar","lat":31.13379,"lon":30.12969,"population":128539},{"id":360754,"name":"Al Manzalah","ascii":"Al Manzalah","lat":31.15823,"lon":31.936,"population":127394},{"id":352354,"name":"Munūf","ascii":"Munuf","lat":30.46597,"lon":30.93199,"population":125707},{"id":360048,"name":"Ashmūn","ascii":"Ashmun","lat":30.29735,"lon":30.97641,"population":124483},{"id":359815,"name":"As Sinbillāwayn","ascii":"As Sinbillawayn","lat":30.88251,"lon":31.46275,"population":124020},{"id":353183,"name":"Maghāghah","ascii":"Maghaghah","lat":28.64776,"lon":30.841,"population":118223},{"id":352913,"name":"Manfalūţ","ascii":"Manfalut","lat":27.3126,"lon":30.96987,"population":117925},{"id":356989,"name":"Fāqūs","ascii":"Faqus","lat":30.72816,"lon":31.79697,"population":116945},{"id":359212,"name":"Banī Mazār","ascii":"Bani Mazar","lat":28.49456,"lon":30.80526,"population":115759},{"id":361329,"name":"Al Fashn","ascii":"Al Fashn","lat":28.82306,"lon":30.89903,"population":112999},{"id":347591,"name":"Ţalkhā","ascii":"Talkha","lat":31.0539,"lon":31.37787,"population":112851},{"id":362973,"name":"Abnūb","ascii":"Abnub","lat":27.26881,"lon":31.15232,"population":111785},{"id":346030,"name":"Zefta","ascii":"Zefta","lat":30.7142,"lon":31.24425,"population":111700},{"id":362004,"name":"Abū Tīj","ascii":"Abu Tij","lat":27.04514,"lon":31.31845,"population":105418},{"id":358269,"name":"Dayrūţ","ascii":"Dayrut","lat":27.55642,"lon":30.81057,"population":102570},{"id":347296,"name":"Ţimā","ascii":"Tima","lat":26.90843,"lon":31.43469,"population":101130},{"id":358172,"name":"Dikirnis","ascii":"Dikirnis","lat":31.08898,"lon":31.59478,"population":101082},{"id":361029,"name":"Al Jammālīyah","ascii":"Al Jammaliyah","lat":31.18065,"lon":31.86497,"population":99641},{"id":360526,"name":"Al Qūşīyah","ascii":"Al Qusiyah","lat":27.44023,"lon":30.81712,"population":99598},{"id":352352,"name":"Minyā al Qamḩ","ascii":"Minya al Qamh","lat":30.51552,"lon":31.34629,"population":99284},{"id":12640364,"name":"Ash-Shaykh Zāyid","ascii":"Ash-Shaykh Zayid","lat":30.02,"lon":31,"population":95854},{"id":358870,"name":"Bibā","ascii":"Biba","lat":28.92406,"lon":30.98544,"population":94677},{"id":360542,"name":"Al Qurayn","ascii":"Al Qurayn","lat":30.61618,"lon":31.73514,"population":94632},{"id":359576,"name":"Awsīm","ascii":"Awsim","lat":30.12303,"lon":31.13571,"population":94174},{"id":356806,"name":"Fuwwah","ascii":"Fuwwah","lat":31.20365,"lon":30.54908,"population":93392},{"id":7799998,"name":"El Shorouk","ascii":"El Shorouk","lat":30.13806,"lon":31.61556,"population":91899},{"id":360773,"name":"Al Minshāh","ascii":"Al Minshah","lat":26.4775,"lon":31.80394,"population":91149},{"id":361473,"name":"Al Badrashayn","ascii":"Al Badrashayn","lat":29.85,"lon":31.26667,"population":90833},{"id":362277,"name":"Abū Qurqāş","ascii":"Abu Qurqas","lat":27.93043,"lon":30.83826,"population":90266},{"id":358726,"name":"Biyalā","ascii":"Biyala","lat":31.17419,"lon":31.2218,"population":89068},{"id":349715,"name":"Samannūd","ascii":"Samannud","lat":30.9616,"lon":31.24069,"population":87921},{"id":362865,"name":"Abū an Numrus","ascii":"Abu an Numrus","lat":29.95,"lon":31.2,"population":86601},{"id":355648,"name":"Ibshawāy","ascii":"Ibshaway","lat":29.35896,"lon":30.68061,"population":86186},{"id":350422,"name":"Qūş","ascii":"Qus","lat":25.91544,"lon":32.76287,"population":84386},{"id":360615,"name":"Al Qanāţir al Khayrīyah","ascii":"Al Qanatir al Khayriyah","lat":30.19327,"lon":31.13703,"population":83568},{"id":354365,"name":"Kafr az Zayyāt","ascii":"Kafr az Zayyat","lat":30.8248,"lon":30.81805,"population":83348},{"id":360923,"name":"Al Khārjah","ascii":"Al Kharjah","lat":25.45101,"lon":30.54653,"population":83108},{"id":12640357,"name":"Al-Khārijah","ascii":"Al-Kharijah","lat":25.25,"lon":30.55,"population":83108},{"id":356000,"name":"Ḩawsh ‘Īsá","ascii":"Hawsh 'Isa","lat":30.9128,"lon":30.29019,"population":82999},{"id":352344,"name":"Minyat an Naşr","ascii":"Minyat an Nasr","lat":31.12624,"lon":31.64313,"population":82429},{"id":352628,"name":"Maţāy","ascii":"Matay","lat":28.41866,"lon":30.77861,"population":82328},{"id":360928,"name":"Al Khānkah","ascii":"Al Khankah","lat":30.21035,"lon":31.36812,"population":81646},{"id":358095,"name":"Diyarb Najm","ascii":"Diyarb Najm","lat":30.75438,"lon":31.44016,"population":80954},{"id":355635,"name":"Edfu","nameKo":"에드푸","ascii":"Edfu","lat":24.97916,"lon":32.87722,"population":79510},{"id":360170,"name":"Armant","ascii":"Armant","lat":25.61988,"lon":32.54305,"population":78695},{"id":347883,"name":"Sirs al Layyānah","ascii":"Sirs al Layyanah","lat":30.4428,"lon":30.96975,"population":78168},{"id":355417,"name":"Ītāy al Bārūd","ascii":"Itay al Barud","lat":30.88697,"lon":30.66724,"population":77606},{"id":354981,"name":"Juhaynah","ascii":"Juhaynah","lat":26.67418,"lon":31.49686,"population":76555},{"id":349114,"name":"Shirbīn","ascii":"Shirbin","lat":31.19688,"lon":31.5243,"population":76081},{"id":359953,"name":"Ash Shuhadā’","ascii":"Ash Shuhada'","lat":30.59683,"lon":30.89931,"population":76071},{"id":352679,"name":"Mashtūl as Sūq","ascii":"Mashtul as Suq","lat":30.36056,"lon":31.3776,"population":75837},{"id":358970,"name":"Basyūn","ascii":"Basyun","lat":30.93976,"lon":30.81338,"population":75084},{"id":355939,"name":"Hihyā","ascii":"Hihya","lat":30.6713,"lon":31.58801,"population":74823},{"id":355420,"name":"Iţsā","ascii":"Itsa","lat":29.2376,"lon":30.78944,"population":74357},{"id":349156,"name":"Shibīn al Qanāţir","ascii":"Shibin al Qanatir","lat":30.31269,"lon":31.32018,"population":73711},{"id":347542,"name":"Ţāmiyah","ascii":"Tamiyah","lat":29.47639,"lon":30.96119,"population":73070},{"id":347612,"name":"Talā","ascii":"Tala","lat":30.6798,"lon":30.94364,"population":72536},{"id":353223,"name":"Madīnat as Sādāt","ascii":"Madinat as Sadat","lat":30.36742,"lon":30.50871,"population":71501},{"id":356933,"name":"Farshūţ","ascii":"Farshut","lat":26.05501,"lon":32.16274,"population":71013},{"id":361301,"name":"Al Ghanāyim","ascii":"Al Ghanayim","lat":26.87524,"lon":31.32963,"population":70884},{"id":360612,"name":"Al Qanāyāt","ascii":"Al Qanayat","lat":30.61927,"lon":31.46165,"population":70687},{"id":361827,"name":"Ad Dilinjāt","ascii":"Ad Dilinjat","lat":30.82796,"lon":30.53552,"population":68901},{"id":361435,"name":"Al Balyanā","ascii":"Al Balyana","lat":26.23648,"lon":32.00387,"population":68413},{"id":362882,"name":"Abū al Maţāmīr","ascii":"Abu al Matamir","lat":30.91018,"lon":30.17438,"population":66946},{"id":350370,"name":"Quwaysinā","ascii":"Quwaysina","lat":30.56482,"lon":31.15777,"population":65690},{"id":347751,"name":"Sumusţā al Waqf","ascii":"Sumusta al Waqf","lat":28.92095,"lon":30.85367,"population":64965},{"id":358115,"name":"Dishnā","ascii":"Dishna","lat":26.12242,"lon":32.46749,"population":64744},{"id":355596,"name":"Ihnāsīyah","ascii":"Ihnasiyah","lat":29.09285,"lon":31.02043,"population":64058},{"id":361457,"name":"Al Bājūr","ascii":"Al Bajur","lat":30.43046,"lon":31.03679,"population":62961},{"id":358388,"name":"Darāw","ascii":"Daraw","lat":24.40796,"lon":32.92324,"population":61790},{"id":359900,"name":"Aş Şaff","ascii":"As Saff","lat":29.56472,"lon":31.28111,"population":61531},{"id":362552,"name":"Abū Ḩummuş","ascii":"Abu Hummus","lat":31.09311,"lon":30.31418,"population":61388},{"id":358274,"name":"Dayr Mawās","ascii":"Dayr Mawas","lat":27.64148,"lon":30.85012,"population":60835},{"id":361360,"name":"Al Burj","ascii":"Al Burj","lat":31.58229,"lon":30.98095,"population":60320},{"id":351434,"name":"Nag Hammâdi","ascii":"Nag Hammadi","lat":26.04949,"lon":32.24142,"population":59601},{"id":433774,"name":"Aş Şāliḩīyah al Jadīdah","ascii":"As Salihiyah al Jadidah","lat":30.63146,"lon":31.93927,"population":59320},{"id":351708,"name":"Nabarūh","ascii":"Nabaruh","lat":31.09755,"lon":31.30312,"population":59202},{"id":361213,"name":"Al Ḩāmūl","ascii":"Al Hamul","lat":31.31146,"lon":31.14766,"population":58430},{"id":360464,"name":"Al Wāsiţah","ascii":"Al Wasitah","lat":29.33778,"lon":31.20556,"population":57870},{"id":361478,"name":"Al Badārī","ascii":"Al Badari","lat":26.99306,"lon":31.41605,"population":56033},{"id":353828,"name":"Kawm Ḩamādah","ascii":"Kawm Hamadah","lat":30.76128,"lon":30.69972,"population":55652},{"id":421251,"name":"Dumyāţ al Jadīdah","ascii":"Dumyat al Jadidah","lat":31.43482,"lon":31.67506,"population":54508},{"id":359892,"name":"As Sāḩil","ascii":"As Sahil","lat":27.06309,"lon":31.34425,"population":54094},{"id":361103,"name":"Al Ibrāhīmīyah","ascii":"Al Ibrahimiyah","lat":30.71877,"lon":31.56299,"population":53791},{"id":360748,"name":"Al Marāghah","ascii":"Al Maraghah","lat":26.69981,"lon":31.60464,"population":53643},{"id":358620,"name":"Safaga","nameKo":"사파가","ascii":"Safaga","lat":26.74906,"lon":33.93891,"population":53639},{"id":361119,"name":"‘Izbat ‘Alī as Sayyid","ascii":"'Izbat 'Ali as Sayyid","lat":31.15671,"lon":30.14775,"population":53079},{"id":347236,"name":"Ţūkh","ascii":"Tukh","lat":30.35487,"lon":31.20105,"population":52593},{"id":358683,"name":"Būlāq Abū al ‘Ilā","ascii":"Bulaq Abu al 'Ila","lat":30.06041,"lon":31.23147,"population":51741},{"id":359304,"name":"Balţīm","ascii":"Baltim","lat":31.55582,"lon":31.08918,"population":51280},{"id":358769,"name":"Birkat as Sab‘","ascii":"Birkat as Sab'","lat":30.62914,"lon":31.08235,"population":50924},{"id":361125,"name":"Al Ḩusaynīyah","ascii":"Al Husayniyah","lat":30.86163,"lon":31.91809,"population":50651},{"id":350797,"name":"Qillīn","ascii":"Qillin","lat":31.0475,"lon":30.85487,"population":48233},{"id":352124,"name":"Mīt Salsīl","ascii":"Mit Salsil","lat":31.16757,"lon":31.80125,"population":48166},{"id":354699,"name":"Kafr al Baţţīkh","ascii":"Kafr al Battikh","lat":31.40398,"lon":31.73778,"population":47198},{"id":361702,"name":"Aga","ascii":"Aga","lat":30.94162,"lon":31.29039,"population":47013},{"id":346201,"name":"Zaafarana","ascii":"Zaafarana","lat":29.11007,"lon":32.66012,"population":46993},{"id":359710,"name":"At Tall al Kabīr","ascii":"At Tall al Kabir","lat":30.54323,"lon":31.78504,"population":46962},{"id":359169,"name":"Banī ‘Ubayd","ascii":"Bani 'Ubayd","lat":27.95243,"lon":30.78082,"population":46060},{"id":434129,"name":"Burj al ‘Arab al Jadīdah","ascii":"Burj al 'Arab al Jadidah","lat":30.88525,"lon":29.57721,"population":45865},{"id":359849,"name":"As Sanţah","ascii":"As Santah","lat":30.74614,"lon":31.12964,"population":45813},{"id":361495,"name":"Al ‘Ayyāţ","ascii":"Al 'Ayyat","lat":29.61972,"lon":31.2575,"population":45793},{"id":354440,"name":"Aş Şalāḩāt","ascii":"As Salahat","lat":31.00205,"lon":31.62626,"population":45557},{"id":7521348,"name":"Ain Sukhna","ascii":"Ain Sukhna","lat":29.60018,"lon":32.31671,"population":45552},{"id":359541,"name":"Al ‘Ayn as Sukhnah","ascii":"Al 'Ayn as Sukhnah","lat":29.58902,"lon":32.33597,"population":45552},{"id":354605,"name":"Kafr al Kurdī","ascii":"Kafr al Kurdi","lat":31.16844,"lon":31.7655,"population":44905},{"id":350207,"name":"Ras Gharib","ascii":"Ras Gharib","lat":28.35831,"lon":33.07829,"population":44852},{"id":348112,"name":"Sīdī Sālim","ascii":"Sidi Salim","lat":31.27133,"lon":30.78617,"population":44709},{"id":354105,"name":"Kafr Şaqr","ascii":"Kafr Saqr","lat":30.79336,"lon":31.62575,"population":44529},{"id":360150,"name":"Ar Raḩmānīyah","ascii":"Ar Rahmaniyah","lat":31.10483,"lon":30.64135,"population":44482},{"id":350350,"name":"Rafaḩ","ascii":"Rafah","lat":31.28204,"lon":34.23869,"population":44215},{"id":351748,"name":"Muţūbas","ascii":"Mutubas","lat":31.29443,"lon":30.52248,"population":43899},{"id":356945,"name":"Fāraskūr","ascii":"Faraskur","lat":31.32977,"lon":31.71507,"population":43400},{"id":362615,"name":"Abū Ḩammād","ascii":"Abu Hammad","lat":30.53766,"lon":31.67875,"population":43001},{"id":349058,"name":"Shubrākhīt","ascii":"Shubrakhit","lat":31.02795,"lon":30.71493,"population":41233},{"id":434170,"name":"Madīnat Wādī an Naţrūn","ascii":"Madinat Wadi an Natrun","lat":30.37746,"lon":30.35032,"population":41186},{"id":9073431,"name":"Aţ Ţārif","ascii":"At Tarif","lat":25.73826,"lon":32.63684,"population":38871},{"id":349340,"name":"Sharm el-Sheikh","nameKo":"샤름엘셰이크","ascii":"Sharm el-Sheikh","lat":27.91582,"lon":34.32995,"population":38478},{"id":359678,"name":"El-Tor","ascii":"El-Tor","lat":28.24168,"lon":33.6222,"population":38285},{"id":348548,"name":"Sīdī Barānī","ascii":"Sidi Barani","lat":31.61166,"lon":25.92539,"population":38253},{"id":444473,"name":"Dār as Salām","ascii":"Dar as Salam","lat":26.27845,"lon":32.05608,"population":38008},{"id":355392,"name":"‘Izbat al Burj","ascii":"`Izbat al Burj","lat":31.5084,"lon":31.84106,"population":37953},{"id":347749,"name":"Sumusţā as Sulţānī","ascii":"Sumusta as Sultani","lat":28.91667,"lon":30.85,"population":37260},{"id":350831,"name":"Qahā","ascii":"Qaha","lat":30.28011,"lon":31.20531,"population":36225},{"id":357039,"name":"Fāyīd","ascii":"Fayid","lat":30.31263,"lon":32.30935,"population":35066},{"id":360471,"name":"Al Waqf","ascii":"Al Waqf","lat":26.08657,"lon":32.42265,"population":34723},{"id":360819,"name":"Al Maḩmūdīyah","ascii":"Al Mahmudiyah","lat":31.18352,"lon":30.52448,"population":34660},{"id":349600,"name":"Sāqultah","ascii":"Saqultah","lat":26.65817,"lon":31.67137,"population":34273},{"id":415561,"name":"Badr","ascii":"Badr","lat":30.136,"lon":31.715,"population":32940},{"id":361405,"name":"Al Başalīyah Baḩrī","ascii":"Al Basaliyah Bahri","lat":25.15,"lon":32.71667,"population":32920},{"id":409361,"name":"Awlād Şaqr","ascii":"Awlad Saqr","lat":30.93055,"lon":31.69864,"population":32840},{"id":362028,"name":"Abu Suweir-el-Mahatta","ascii":"Abu Suweir-el-Mahatta","lat":30.56977,"lon":32.1146,"population":32763},{"id":433441,"name":"Banī Suwayf al Jadīdah","ascii":"Bani Suwayf al Jadidah","lat":29.033,"lon":31.11408,"population":32278},{"id":350376,"name":"Quţūr","ascii":"Qutur","lat":30.97225,"lon":30.95614,"population":32043},{"id":353136,"name":"Maḩallat Damanah","ascii":"Mahallat Damanah","lat":31.07287,"lon":31.49503,"population":31921},{"id":360610,"name":"Al Qanţarah","ascii":"Al Qantarah","lat":30.85711,"lon":32.31183,"population":31808},{"id":12640363,"name":"Ar-Rawḍah","ascii":"Ar-Rawdah","lat":31.32336,"lon":31.76122,"population":31240},{"id":349653,"name":"Şān al Ḩajar al Qiblīyah","ascii":"San al Hajar al Qibliyah","lat":30.97478,"lon":31.87231,"population":30969},{"id":354076,"name":"Kafr Shukr","ascii":"Kafr Shukr","lat":30.54972,"lon":31.24444,"population":30948},{"id":347422,"name":"Ţūd","ascii":"Tud","lat":25.58278,"lon":32.5329,"population":30780},{"id":348962,"name":"Şidfā","ascii":"Sidfa","lat":26.96637,"lon":31.37953,"population":30228},{"id":359841,"name":"As Sarw","ascii":"As Sarw","lat":31.23867,"lon":31.65379,"population":29286},{"id":13118928,"name":"New Bani Sewif City","ascii":"New Bani Sewif City","lat":29.03556,"lon":31.11792,"population":29117},{"id":348507,"name":"Sīdī Ghāzī","ascii":"Sidi Ghazi","lat":31.21114,"lon":31.05119,"population":28136},{"id":421600,"name":"Badr","ascii":"Badr","lat":30.575,"lon":30.71111,"population":28091},{"id":361871,"name":"El Dabaa","ascii":"El Dabaa","lat":31.02819,"lon":28.44498,"population":27697},{"id":419435,"name":"Az Zarqā","ascii":"Az Zarqa","lat":31.20864,"lon":31.63528,"population":26955},{"id":359749,"name":"Aţfīḩ","ascii":"Atfih","lat":29.4075,"lon":31.2525,"population":26943},{"id":351766,"name":"Mūţ","ascii":"Mut","lat":25.48742,"lon":28.97918,"population":26820},{"id":351356,"name":"Naqādah","ascii":"Naqadah","lat":25.90107,"lon":32.72392,"population":26774},{"id":353471,"name":"Ash Shaykh Zuwayd","ascii":"Ash Shaykh Zuwayd","lat":31.2163,"lon":34.11074,"population":26713},{"id":410142,"name":"Bi’r al ‘Abd","ascii":"Bi'r al 'Abd","lat":31.01887,"lon":33.0098,"population":26330},{"id":361098,"name":"Al ‘Idwah","ascii":"Al 'Idwah","lat":28.69919,"lon":30.7673,"population":26092},{"id":347863,"name":"Sīwah","ascii":"Siwah","lat":29.2032,"lon":25.51965,"population":25031},{"id":360531,"name":"Al Quşayr","ascii":"Al Qusayr","lat":26.10611,"lon":34.27716,"population":24653},{"id":360577,"name":"Al Qaşşāşīn","ascii":"Al Qassasin","lat":30.56412,"lon":31.93386,"population":24364},{"id":416047,"name":"Ar Riyāḑ","ascii":"Ar Riyad","lat":31.24193,"lon":30.94504,"population":24254},{"id":350560,"name":"Qifţ","ascii":"Qift","lat":25.99845,"lon":32.81808,"population":24010},{"id":12640381,"name":"Yūsuf aṣ-Ṣiddīq","ascii":"Yusuf as-Siddiq","lat":29.385,"lon":30.557,"population":23965},{"id":361391,"name":"Al Bayāḑīyah","ascii":"Al Bayadiyah","lat":25.66477,"lon":32.63539,"population":23550},{"id":408919,"name":"An Nūbārīyah","ascii":"An Nubariyah","lat":30.6687,"lon":30.07391,"population":23282},{"id":352440,"name":"Munsha‘at Abū ‘Umar","ascii":"Munsha'at Abu 'Umar","lat":30.90711,"lon":32.02341,"population":22543},{"id":358631,"name":"Burj al ‘Arab","ascii":"Burj al 'Arab","lat":30.90316,"lon":29.55276,"population":22444},{"id":434418,"name":"An Nāşirīyah","ascii":"An Nasiriyah","lat":27.20583,"lon":31.19639,"population":22435},{"id":359823,"name":"As Sibā‘īyah","ascii":"As Siba'iyah","lat":25.19413,"lon":32.6771,"population":21610},{"id":352250,"name":"Mīt Abū Ghālib","ascii":"Mit Abu Ghalib","lat":31.28837,"lon":31.67719,"population":20470},{"id":355174,"name":"Jarājūs","ascii":"Jarajus","lat":25.87198,"lon":32.75585,"population":20427},{"id":347289,"name":"Timayy al Imdīd","ascii":"Timayy al Imdid","lat":30.94384,"lon":31.52926,"population":20389},{"id":359480,"name":"Az Zaynīyah Qiblī","ascii":"Az Zayniyah Qibli","lat":25.75089,"lon":32.6776,"population":20000},{"id":12640361,"name":"An-Najaylah","ascii":"An-Najaylah","lat":31.4071,"lon":26.5832,"population":19768},{"id":352878,"name":"Manshīyat al Qanāţir","ascii":"Manshiyat al Qanatir","lat":30.18479,"lon":31.10649,"population":19185},{"id":361219,"name":"Al Ḩammām","ascii":"Al Hammam","lat":30.84532,"lon":29.38818,"population":18407},{"id":361995,"name":"Abū Ţisht","ascii":"Abu Tisht","lat":26.12039,"lon":32.09543,"population":18194},{"id":354123,"name":"Kafr Sa‘d","ascii":"Kafr Sa'd","lat":31.35573,"lon":31.68484,"population":18120},{"id":12640359,"name":"Al-Minyā al-Jadīdah","ascii":"Al-Minya al-Jadidah","lat":28.08639,"lon":30.81464,"population":17470},{"id":359867,"name":"As Sallūm","ascii":"As Sallum","lat":31.55371,"lon":25.15793,"population":16545},{"id":360159,"name":"Ar Radīsīyah Qiblī","ascii":"Ar Radisiyah Qibli","lat":24.90652,"lon":32.88563,"population":16190},{"id":361394,"name":"Al Bawīţī","ascii":"Al Bawiti","lat":28.34827,"lon":28.86936,"population":15653},{"id":6692512,"name":"El Gouna","ascii":"El Gouna","lat":27.39417,"lon":33.67825,"population":15000},{"id":8555994,"name":"Shalateen","nameKo":"샬라틴","ascii":"Shalateen","lat":23.13235,"lon":35.59094,"population":12443},{"id":12056179,"name":"Shalātīn","ascii":"Shalatin","lat":23.13905,"lon":35.59821,"population":12421},{"id":350211,"name":"Râs el-Barr","ascii":"Ras el-Barr","lat":31.51027,"lon":31.82851,"population":10213},{"id":352736,"name":"Marsa Alam","ascii":"Marsa Alam","lat":25.06305,"lon":34.89005,"population":10000},{"id":358245,"name":"Dahab","ascii":"Dahab","lat":28.48208,"lon":34.49505,"population":8000},{"id":361612,"name":"Al ‘Alamayn","ascii":"Al `Alamayn","lat":30.83007,"lon":28.95502,"population":7400},{"id":360456,"name":"Al Yāsīnīyah","ascii":"Al Yasiniyah","lat":30.95,"lon":30.06667,"population":6886},{"id":362041,"name":"Abu Simbel","ascii":"Abu Simbel","lat":22.3457,"lon":31.61624,"population":5000},{"id":350893,"name":"Nuwaybi‘a","ascii":"Nuwaybi`a","lat":29.04681,"lon":34.6634,"population":5000},{"id":350661,"name":"Qaşr al Farāfirah","ascii":"Qasr al Farafirah","lat":27.0568,"lon":27.96979,"population":5000},{"id":8521413,"name":"Saint Catherine","ascii":"Saint Catherine","lat":28.56191,"lon":33.94934,"population":4603},{"id":6692518,"name":"Makadi Bay","ascii":"Makadi Bay","lat":26.99123,"lon":33.89952,"population":4000},{"id":11608775,"name":"Munshāt ‘Alī Āghā","ascii":"Munshat 'Ali Agha","lat":31.15791,"lon":30.70177,"population":3847},{"id":346067,"name":"Zāwyat Umm ar Rakham","ascii":"Zawyat Umm ar Rakham","lat":31.39596,"lon":27.04526,"population":2643},{"id":7911550,"name":"Masākin Shirkat Abū al Wafā lil Muqāwalāt wa al Istithmār al ‘Aqārī","ascii":"Masakin Shirkat Abu al Wafa lil Muqawalat wa al Istithmar al 'Aqari","lat":30.03253,"lon":31.29625,"population":2560},{"id":8134082,"name":"Jam‘īyat Iskān aḑ Ḑubbāţ bi Akādīmīyat ash Shurţah","ascii":"Jam'iyat Iskan ad Dubbat bi Akadimiyat ash Shurtah","lat":30.05618,"lon":31.42256,"population":1228},{"id":12536488,"name":"Sānt Kātrīnā","ascii":"SantKatrina","lat":28.56199,"lon":33.95005,"population":0}]