[{"id":1283240,"name":"Kathmandu","nameKo":"카트만두","ascii":"Kathmandu","lat":27.70169,"lon":85.3206,"population":1442271},{"id":1282898,"name":"Pokhara","nameKo":"포카라","ascii":"Pokhara","lat":28.26689,"lon":83.96851,"population":600051},{"id":1283613,"name":"Bharatpur","nameKo":"바랏푸르","ascii":"Bharatpur","lat":27.68027,"lon":84.43647,"population":369377},{"id":1282931,"name":"Pātan","ascii":"Patan","lat":27.67658,"lon":85.31417,"population":299283},{"id":1283581,"name":"Birgañj","ascii":"Birganj","lat":27.01736,"lon":84.88047,"population":268273},{"id":1283582,"name":"Biratnagar","nameKo":"비랏나가르","ascii":"Biratnagar","lat":26.45505,"lon":87.27007,"population":244750},{"id":1283467,"name":"Dhangaḍhi̇̄","ascii":"Dhangadhi","lat":28.70159,"lon":80.58991,"population":204788},{"id":1283339,"name":"Hetauda","ascii":"Hetauda","lat":27.42839,"lon":85.03219,"population":195951},{"id":1283318,"name":"Janakpur","nameKo":"자낙푸르","ascii":"Janakpur","lat":26.72882,"lon":85.92628,"population":195438},{"id":1283562,"name":"Butwāl","ascii":"Butwal","lat":27.70055,"lon":83.44836,"population":195054},{"id":1283460,"name":"Dharān","ascii":"Dharan","lat":26.81436,"lon":87.27972,"population":173096},{"id":6941099,"name":"Nepalgunj","ascii":"Nepalgunj","lat":28.05,"lon":81.61667,"population":166258},{"id":6254843,"name":"Birendranagar","ascii":"Birendranagar","lat":28.59669,"lon":81.61658,"population":154886},{"id":8411054,"name":"Madhyapur Thimi","ascii":"Madhyapur Thimi","lat":27.68056,"lon":85.3875,"population":119955},{"id":1283161,"name":"Lahān","ascii":"Lahan","lat":26.72022,"lon":86.48258,"population":102955},{"id":1283095,"name":"Bhimdatta","ascii":"Bhimdatta","lat":28.96399,"lon":80.17715,"population":88381},{"id":8410807,"name":"Triyuga","ascii":"Triyuga","lat":26.7919,"lon":86.699,"population":71405},{"id":7997918,"name":"Inaruwa","ascii":"Inaruwa","lat":26.60675,"lon":87.1478,"population":70093},{"id":1282884,"name":"Rājbirāj","ascii":"Rajbiraj","lat":26.53968,"lon":86.74796,"population":69803},{"id":1283679,"name":"Banepā","ascii":"Banepa","lat":27.6327,"lon":85.52201,"population":67629},{"id":1283621,"name":"Siddharthanagar","ascii":"Siddharthanagar","lat":27.5,"lon":83.45,"population":63367},{"id":1283368,"name":"Gulariyā","ascii":"Gulariya","lat":28.2058,"lon":81.34532,"population":53107},{"id":1283539,"name":"Chautārā","ascii":"Chautara","lat":27.7763,"lon":85.7127,"population":51347},{"id":1283329,"name":"Īṭahari̇̄","ascii":"Itahari","lat":26.66371,"lon":87.27403,"population":47984},{"id":7963596,"name":"Panauti","ascii":"Panauti","lat":27.58466,"lon":85.52122,"population":46595},{"id":1282666,"name":"Ṭikāpur","ascii":"Tikapur","lat":28.52819,"lon":81.11828,"population":44758},{"id":1283190,"name":"Ki̇̄rtipur","ascii":"Kirtipur","lat":27.67851,"lon":85.27574,"population":44632},{"id":1283546,"name":"Chari̇̄koṭ","ascii":"Charikot","lat":27.66824,"lon":86.0519,"population":40000},{"id":1282635,"name":"Tulsi̇̄pur","ascii":"Tulsipur","lat":28.13328,"lon":82.29803,"population":39058},{"id":6254845,"name":"Dipayal","ascii":"Dipayal","lat":29.26083,"lon":80.94,"population":33968},{"id":1282950,"name":"Panauti̇̄","ascii":"Panauti","lat":27.58447,"lon":85.51487,"population":27602},{"id":1283401,"name":"Gaur","ascii":"Gaur","lat":26.76371,"lon":85.27659,"population":27325},{"id":1282770,"name":"Siraha","ascii":"Siraha","lat":26.65422,"lon":86.20795,"population":24657},{"id":1282714,"name":"Tānsen","ascii":"Tansen","lat":27.86655,"lon":83.54587,"population":23693},{"id":1283323,"name":"Jaleshwar","ascii":"Jaleshwar","lat":26.64921,"lon":85.80017,"population":23573},{"id":1283711,"name":"Bāgluṅ","ascii":"Baglun","lat":28.26728,"lon":83.59956,"population":23296},{"id":1283217,"name":"Khā̃dbāri̇̄","ascii":"Khadbari","lat":27.37647,"lon":87.20773,"population":22903},{"id":1283465,"name":"Dhankutā","ascii":"Dhankuta","lat":26.98333,"lon":87.33333,"population":22084},{"id":1282616,"name":"Wāliṅ","ascii":"Walin","lat":27.9837,"lon":83.75925,"population":21867},{"id":1283496,"name":"Dailekh","ascii":"Dailekh","lat":28.84434,"lon":81.71011,"population":20908},{"id":1283082,"name":"Malaṅgawā","ascii":"Malangawa","lat":26.85622,"lon":85.56032,"population":20284},{"id":1283628,"name":"Bhadrapur","ascii":"Bhadrapur","lat":26.54404,"lon":88.09436,"population":19523},{"id":1283499,"name":"Amargaḍhi̇̄","ascii":"Amargadhi","lat":29.29922,"lon":80.58333,"population":19014},{"id":1283484,"name":"Dārchulā","ascii":"Darchula","lat":29.83,"lon":80.55,"population":18317},{"id":1283333,"name":"Ilām","ascii":"Ilam","lat":26.90943,"lon":87.92824,"population":17491},{"id":1283448,"name":"Dhulikhel","ascii":"Dhulikhel","lat":27.6221,"lon":85.54281,"population":16263},{"id":10316796,"name":"Chapali̇̄ Bhaḍrakāli̇̄","ascii":"Chapali Bhadrakali","lat":27.7821,"lon":85.37426,"population":10827},{"id":8199102,"name":"kankrabari Dovan","ascii":"kankrabari Dovan","lat":27.62881,"lon":85.45934,"population":10000},{"id":1283285,"name":"Jumla","ascii":"Jumla","lat":29.27472,"lon":82.18383,"population":9073},{"id":1283119,"name":"Lobuche","ascii":"Lobuche","lat":27.94806,"lon":86.81017,"population":8767},{"id":1283168,"name":"Kusma","ascii":"Kusma","lat":28.22266,"lon":83.6826,"population":6758},{"id":11154397,"name":"Bhattarai Danda","ascii":"Bhattarai Danda","lat":27.88333,"lon":83.93333,"population":5510},{"id":6254842,"name":"Besisahar","ascii":"Besisahar","lat":28.23111,"lon":84.3775,"population":5427},{"id":1283018,"name":"Nagarkot","ascii":"Nagarkot","lat":27.71522,"lon":85.52075,"population":4000},{"id":1283600,"name":"Bhojpur","ascii":"Bhojpur","lat":27.1715,"lon":87.04607,"population":3250},{"id":6941691,"name":"Chitre","ascii":"Chitre","lat":28.42673,"lon":83.69076,"population":2860},{"id":1283599,"name":"Bhojpur","ascii":"Bhojpur","lat":28.0353,"lon":82.29552,"population":2640},{"id":1283011,"name":"Namche Bazaar","ascii":"Namche Bazaar","lat":27.80528,"lon":86.71058,"population":2324},{"id":11523504,"name":"Dihi","ascii":"Dihi","lat":27.87552,"lon":83.92759,"population":2210},{"id":1283022,"name":"Mustāng","ascii":"Mustang","lat":29.18321,"lon":83.95634,"population":1899},{"id":1283189,"name":"Kodāri̇̄","ascii":"Kodari","lat":27.96228,"lon":85.95167,"population":1600},{"id":1283742,"name":"Achhām","ascii":"Achham","lat":29.05,"lon":81.3,"population":0},{"id":1283662,"name":"Bardiyā","ascii":"Bardiya","lat":28.30058,"lon":81.3536,"population":0},{"id":1283617,"name":"Bhaktapur","nameKo":"박타푸르","ascii":"Bhaktapur","lat":27.67298,"lon":85.43005,"population":0},{"id":1283559,"name":"Chainpur","ascii":"Chainpur","lat":29.55637,"lon":81.19858,"population":0},{"id":1283392,"name":"Ghorahi","ascii":"Ghorahi","lat":28.04324,"lon":82.48625,"population":0},{"id":1283268,"name":"Kalikot District","ascii":"Kalikot District","lat":29.10201,"lon":81.67982,"population":0},{"id":1283150,"name":"Lamjung","ascii":"Lamjung","lat":28.20992,"lon":84.3638,"population":0},{"id":1282887,"name":"Pyūthān","ascii":"Pyuthan","lat":28.08867,"lon":82.88427,"population":0},{"id":1282878,"name":"Rāmechhāp","ascii":"Ramechhap","lat":27.3256,"lon":86.08768,"population":0},{"id":1282826,"name":"Salyān","ascii":"Salyan","lat":28.37858,"lon":82.1703,"population":0},{"id":1282782,"name":"Silgaḍhi̇̄","ascii":"Silgadhi","lat":29.2668,"lon":80.9841,"population":0},{"id":7649119,"name":"Surkhet","ascii":"Surkhet","lat":28.51746,"lon":81.7787,"population":0}]